{
  "directory": "Thorne",
  "summary": {
    "items_total": 72,
    "atlases_generated": 2
  },
  "items": [
    {
      "name": "ear",
      "out_row": 1,
      "out_col": 1,
      "source_file": "dragitem16.tga",
      "src_row": 3,
      "src_col": 2,
      "mode": "grayscale",
      "has_tone_override": true
    },
    {
      "name": "neck",
      "out_row": 1,
      "out_col": 2,
      "source_file": "dragitem1.tga",
      "src_row": 1,
      "src_col": 1,
      "mode": "grayscale",
      "has_tone_override": true
    },
    {
      "name": "head",
      "out_row": 1,
      "out_col": 3,
      "source_file": "dragitem1.tga",
      "src_row": 6,
      "src_col": 4,
      "mode": "grayscale",
      "has_tone_override": true
    },
    {
      "name": "face",
      "out_row": 1,
      "out_col": 4,
      "source_file": "dragitem8.tga",
      "src_row": 3,
      "src_col": 4,
      "mode": "grayscale",
      "has_tone_override": true
    },
    {
      "name": "chest",
      "out_row": 1,
      "out_col": 5,
      "source_file": "dragitem10.tga",
      "src_row": 3,
      "src_col": 3,
      "mode": "grayscale",
      "has_tone_override": true
    },
    {
      "name": "secondary",
      "out_row": 1,
      "out_col": 6,
      "source_file": "dragitem8.tga",
      "src_row": 2,
      "src_col": 5,
      "mode": "grayscale",
      "has_tone_override": true
    },
    {
      "name": "back",
      "out_row": 2,
      "out_col": 1,
      "source_file": "dragitem5.tga",
      "src_row": 2,
      "src_col": 4,
      "mode": "grayscale",
      "has_tone_override": true
    },
    {
      "name": "arms",
      "out_row": 2,
      "out_col": 2,
      "source_file": "dragitem4.tga",
      "src_row": 3,
      "src_col": 5,
      "mode": "grayscale",
      "has_tone_override": true
    },
    {
      "name": "shoulders",
      "out_row": 2,
      "out_col": 3,
      "source_file": "dragitem5.tga",
      "src_row": 4,
      "src_col": 4,
      "mode": "grayscale",
      "has_tone_override": true
    },
    {
      "name": "wrist",
      "out_row": 2,
      "out_col": 4,
      "source_file": "dragitem1.tga",
      "src_row": 4,
      "src_col": 4,
      "mode": "grayscale",
      "has_tone_override": true
    },
    {
      "name": "belt",
      "out_row": 2,
      "out_col": 5,
      "source_file": "dragitem2.tga",
      "src_row": 5,
      "src_col": 5,
      "mode": "grayscale",
      "has_tone_override": true
    },
    {
      "name": "range",
      "out_row": 2,
      "out_col": 6,
      "source_file": "dragitem13.tga",
      "src_row": 2,
      "src_col": 5,
      "mode": "grayscale",
      "has_tone_override": true
    },
    {
      "name": "hands",
      "out_row": 3,
      "out_col": 1,
      "source_file": "dragitem4.tga",
      "src_row": 5,
      "src_col": 5,
      "mode": "grayscale",
      "has_tone_override": true
    },
    {
      "name": "fingers",
      "out_row": 3,
      "out_col": 2,
      "source_file": "dragitem4.tga",
      "src_row": 5,
      "src_col": 1,
      "mode": "grayscale",
      "has_tone_override": true
    },
    {
      "name": "legs",
      "out_row": 3,
      "out_col": 3,
      "source_file": "dragitem4.tga",
      "src_row": 4,
      "src_col": 5,
      "mode": "grayscale",
      "has_tone_override": true
    },
    {
      "name": "feet",
      "out_row": 3,
      "out_col": 4,
      "source_file": "dragitem4.tga",
      "src_row": 2,
      "src_col": 5,
      "mode": "grayscale",
      "has_tone_override": true
    },
    {
      "name": "primary",
      "out_row": 3,
      "out_col": 5,
      "source_file": "dragitem3.tga",
      "src_row": 3,
      "src_col": 1,
      "mode": "grayscale",
      "has_tone_override": true
    },
    {
      "name": "ammo",
      "out_row": 3,
      "out_col": 6,
      "source_file": "dragitem21.tga",
      "src_row": 1,
      "src_col": 2,
      "mode": "grayscale",
      "has_tone_override": true
    },
    {
      "name": "bag",
      "out_row": 4,
      "out_col": 1,
      "source_file": "dragitem2.tga",
      "src_row": 4,
      "src_col": 1,
      "mode": "grayscale",
      "has_tone_override": true
    },
    {
      "name": "backpack",
      "out_row": 4,
      "out_col": 2,
      "source_file": "dragitem2.tga",
      "src_row": 6,
      "src_col": 5,
      "mode": "grayscale",
      "has_tone_override": true
    },
    {
      "name": "satchel",
      "out_row": 4,
      "out_col": 3,
      "source_file": "dragitem6.tga",
      "src_row": 4,
      "src_col": 2,
      "mode": "grayscale",
      "has_tone_override": true
    },
    {
      "name": "pack",
      "out_row": 4,
      "out_col": 4,
      "source_file": "dragitem11.tga",
      "src_row": 1,
      "src_col": 5,
      "mode": "grayscale",
      "has_tone_override": true
    },
    {
      "name": "box",
      "out_row": 4,
      "out_col": 5,
      "source_file": "dragitem4.tga",
      "src_row": 2,
      "src_col": 1,
      "mode": "grayscale",
      "has_tone_override": true
    },
    {
      "name": "open_box",
      "out_row": 4,
      "out_col": 6,
      "source_file": "dragitem7.tga",
      "src_row": 3,
      "src_col": 2,
      "mode": "grayscale",
      "has_tone_override": true
    },
    {
      "name": "empty",
      "out_row": 5,
      "out_col": 1,
      "source_file": "placeholder.tga",
      "src_row": 1,
      "src_col": 1,
      "mode": "empty",
      "has_tone_override": false
    },
    {
      "name": "treasurechest",
      "out_row": 5,
      "out_col": 2,
      "source_file": "dragitem10.tga",
      "src_row": 1,
      "src_col": 3,
      "mode": "grayscale",
      "has_tone_override": true
    },
    {
      "name": "spellbook",
      "out_row": 5,
      "out_col": 3,
      "source_file": "dragitem8.tga",
      "src_row": 2,
      "src_col": 5,
      "mode": "grayscale",
      "has_tone_override": true
    },
    {
      "name": "lantern",
      "out_row": 5,
      "out_col": 4,
      "source_file": "dragitem7.tga",
      "src_row": 2,
      "src_col": 3,
      "mode": "grayscale",
      "has_tone_override": true
    },
    {
      "name": "spell",
      "out_row": 5,
      "out_col": 5,
      "source_file": "dragitem1.tga",
      "src_row": 5,
      "src_col": 1,
      "mode": "grayscale",
      "has_tone_override": true
    },
    {
      "name": "empty_row5_col6",
      "out_row": 5,
      "out_col": 6,
      "source_file": "placeholder.tga",
      "src_row": 1,
      "src_col": 1,
      "mode": "empty",
      "has_tone_override": false
    },
    {
      "name": "logo_1",
      "out_row": 6,
      "out_col": 1,
      "source_file": "logo_atlas_thorne01.tga",
      "src_row": 1,
      "src_col": 1,
      "mode": "invert_impression",
      "has_tone_override": false
    },
    {
      "name": "logo_2",
      "out_row": 6,
      "out_col": 2,
      "source_file": "logo_atlas_thorne01.tga",
      "src_row": 1,
      "src_col": 2,
      "mode": "invert_impression",
      "has_tone_override": false
    },
    {
      "name": "logo_3",
      "out_row": 6,
      "out_col": 3,
      "source_file": "logo_atlas_thorne01.tga",
      "src_row": 1,
      "src_col": 3,
      "mode": "invert_impression",
      "has_tone_override": false
    },
    {
      "name": "logo_4",
      "out_row": 6,
      "out_col": 4,
      "source_file": "logo_atlas_thorne01.tga",
      "src_row": 1,
      "src_col": 4,
      "mode": "invert_impression",
      "has_tone_override": false
    },
    {
      "name": "logo_5",
      "out_row": 6,
      "out_col": 5,
      "source_file": "logo_atlas_thorne01.tga",
      "src_row": 1,
      "src_col": 5,
      "mode": "invert_impression",
      "has_tone_override": false
    },
    {
      "name": "logo_6",
      "out_row": 6,
      "out_col": 6,
      "source_file": "logo_atlas_thorne01.tga",
      "src_row": 1,
      "src_col": 6,
      "mode": "invert_impression",
      "has_tone_override": false
    },
    {
      "name": "ear",
      "out_row": 1,
      "out_col": 1,
      "source_file": "dragitem16.tga",
      "src_row": 3,
      "src_col": 2,
      "mode": "grayscale",
      "has_tone_override": true
    },
    {
      "name": "neck",
      "out_row": 1,
      "out_col": 2,
      "source_file": "dragitem1.tga",
      "src_row": 1,
      "src_col": 1,
      "mode": "grayscale",
      "has_tone_override": true
    },
    {
      "name": "head",
      "out_row": 1,
      "out_col": 3,
      "source_file": "dragitem1.tga",
      "src_row": 6,
      "src_col": 4,
      "mode": "grayscale",
      "has_tone_override": true
    },
    {
      "name": "face",
      "out_row": 1,
      "out_col": 4,
      "source_file": "dragitem8.tga",
      "src_row": 3,
      "src_col": 4,
      "mode": "grayscale",
      "has_tone_override": true
    },
    {
      "name": "chest",
      "out_row": 1,
      "out_col": 5,
      "source_file": "dragitem10.tga",
      "src_row": 3,
      "src_col": 3,
      "mode": "grayscale",
      "has_tone_override": true
    },
    {
      "name": "secondary",
      "out_row": 1,
      "out_col": 6,
      "source_file": "dragitem8.tga",
      "src_row": 2,
      "src_col": 5,
      "mode": "grayscale",
      "has_tone_override": true
    },
    {
      "name": "back",
      "out_row": 2,
      "out_col": 1,
      "source_file": "dragitem5.tga",
      "src_row": 2,
      "src_col": 4,
      "mode": "grayscale",
      "has_tone_override": true
    },
    {
      "name": "arms",
      "out_row": 2,
      "out_col": 2,
      "source_file": "dragitem4.tga",
      "src_row": 3,
      "src_col": 5,
      "mode": "grayscale",
      "has_tone_override": true
    },
    {
      "name": "shoulders",
      "out_row": 2,
      "out_col": 3,
      "source_file": "dragitem5.tga",
      "src_row": 4,
      "src_col": 4,
      "mode": "grayscale",
      "has_tone_override": true
    },
    {
      "name": "wrist",
      "out_row": 2,
      "out_col": 4,
      "source_file": "dragitem1.tga",
      "src_row": 4,
      "src_col": 4,
      "mode": "grayscale",
      "has_tone_override": true
    },
    {
      "name": "belt",
      "out_row": 2,
      "out_col": 5,
      "source_file": "dragitem2.tga",
      "src_row": 5,
      "src_col": 5,
      "mode": "grayscale",
      "has_tone_override": true
    },
    {
      "name": "range",
      "out_row": 2,
      "out_col": 6,
      "source_file": "dragitem13.tga",
      "src_row": 2,
      "src_col": 5,
      "mode": "grayscale",
      "has_tone_override": true
    },
    {
      "name": "hands",
      "out_row": 3,
      "out_col": 1,
      "source_file": "dragitem4.tga",
      "src_row": 5,
      "src_col": 5,
      "mode": "grayscale",
      "has_tone_override": true
    },
    {
      "name": "fingers",
      "out_row": 3,
      "out_col": 2,
      "source_file": "dragitem4.tga",
      "src_row": 5,
      "src_col": 1,
      "mode": "grayscale",
      "has_tone_override": true
    },
    {
      "name": "legs",
      "out_row": 3,
      "out_col": 3,
      "source_file": "dragitem4.tga",
      "src_row": 4,
      "src_col": 5,
      "mode": "grayscale",
      "has_tone_override": true
    },
    {
      "name": "feet",
      "out_row": 3,
      "out_col": 4,
      "source_file": "dragitem4.tga",
      "src_row": 2,
      "src_col": 5,
      "mode": "grayscale",
      "has_tone_override": true
    },
    {
      "name": "primary",
      "out_row": 3,
      "out_col": 5,
      "source_file": "dragitem3.tga",
      "src_row": 3,
      "src_col": 1,
      "mode": "grayscale",
      "has_tone_override": true
    },
    {
      "name": "ammo",
      "out_row": 3,
      "out_col": 6,
      "source_file": "dragitem21.tga",
      "src_row": 1,
      "src_col": 2,
      "mode": "grayscale",
      "has_tone_override": true
    },
    {
      "name": "bag",
      "out_row": 4,
      "out_col": 1,
      "source_file": "dragitem2.tga",
      "src_row": 4,
      "src_col": 1,
      "mode": "grayscale",
      "has_tone_override": true
    },
    {
      "name": "backpack",
      "out_row": 4,
      "out_col": 2,
      "source_file": "dragitem2.tga",
      "src_row": 6,
      "src_col": 5,
      "mode": "grayscale",
      "has_tone_override": true
    },
    {
      "name": "satchel",
      "out_row": 4,
      "out_col": 3,
      "source_file": "dragitem6.tga",
      "src_row": 4,
      "src_col": 2,
      "mode": "grayscale",
      "has_tone_override": true
    },
    {
      "name": "pack",
      "out_row": 4,
      "out_col": 4,
      "source_file": "dragitem11.tga",
      "src_row": 1,
      "src_col": 5,
      "mode": "grayscale",
      "has_tone_override": true
    },
    {
      "name": "box",
      "out_row": 4,
      "out_col": 5,
      "source_file": "dragitem4.tga",
      "src_row": 2,
      "src_col": 1,
      "mode": "grayscale",
      "has_tone_override": true
    },
    {
      "name": "open_box",
      "out_row": 4,
      "out_col": 6,
      "source_file": "dragitem7.tga",
      "src_row": 3,
      "src_col": 2,
      "mode": "grayscale",
      "has_tone_override": true
    },
    {
      "name": "empty",
      "out_row": 5,
      "out_col": 1,
      "source_file": "placeholder.tga",
      "src_row": 1,
      "src_col": 1,
      "mode": "empty",
      "has_tone_override": false
    },
    {
      "name": "treasurechest",
      "out_row": 5,
      "out_col": 2,
      "source_file": "dragitem10.tga",
      "src_row": 1,
      "src_col": 3,
      "mode": "grayscale",
      "has_tone_override": true
    },
    {
      "name": "spellbook",
      "out_row": 5,
      "out_col": 3,
      "source_file": "dragitem8.tga",
      "src_row": 2,
      "src_col": 5,
      "mode": "grayscale",
      "has_tone_override": true
    },
    {
      "name": "lantern",
      "out_row": 5,
      "out_col": 4,
      "source_file": "dragitem7.tga",
      "src_row": 2,
      "src_col": 3,
      "mode": "grayscale",
      "has_tone_override": true
    },
    {
      "name": "spell",
      "out_row": 5,
      "out_col": 5,
      "source_file": "dragitem1.tga",
      "src_row": 5,
      "src_col": 1,
      "mode": "grayscale",
      "has_tone_override": true
    },
    {
      "name": "empty_row5_col6",
      "out_row": 5,
      "out_col": 6,
      "source_file": "placeholder.tga",
      "src_row": 1,
      "src_col": 1,
      "mode": "empty",
      "has_tone_override": false
    },
    {
      "name": "logo_1",
      "out_row": 6,
      "out_col": 1,
      "source_file": "logo_atlas_thorne01.tga",
      "src_row": 1,
      "src_col": 1,
      "mode": "invert_impression",
      "has_tone_override": false
    },
    {
      "name": "logo_2",
      "out_row": 6,
      "out_col": 2,
      "source_file": "logo_atlas_thorne01.tga",
      "src_row": 1,
      "src_col": 2,
      "mode": "invert_impression",
      "has_tone_override": false
    },
    {
      "name": "logo_3",
      "out_row": 6,
      "out_col": 3,
      "source_file": "logo_atlas_thorne01.tga",
      "src_row": 1,
      "src_col": 3,
      "mode": "invert_impression",
      "has_tone_override": false
    },
    {
      "name": "logo_4",
      "out_row": 6,
      "out_col": 4,
      "source_file": "logo_atlas_thorne01.tga",
      "src_row": 1,
      "src_col": 4,
      "mode": "invert_impression",
      "has_tone_override": false
    },
    {
      "name": "logo_5",
      "out_row": 6,
      "out_col": 5,
      "source_file": "logo_atlas_thorne01.tga",
      "src_row": 1,
      "src_col": 5,
      "mode": "invert_impression",
      "has_tone_override": false
    },
    {
      "name": "logo_6",
      "out_row": 6,
      "out_col": 6,
      "source_file": "logo_atlas_thorne01.tga",
      "src_row": 1,
      "src_col": 6,
      "mode": "invert_impression",
      "has_tone_override": false
    }
  ],
  "output_files": [
    "item_atlas_thorne01.tga",
    "item_icons_thorne01.tga"
  ],
  "errors": []
}